{"coord":{"lon":-80.8431,"lat":35.2271},"weather":[{"id":800,"main":"Clear","description":"clear sky","icon":"01n"}],"base":"stations","main":{"temp":26.45,"feels_like":26.45,"temp_min":23.65,"temp_max":27.51,"pressure":1018,"humidity":70,"sea_level":1018,"grnd_level":994},"visibility":10000,"wind":{"speed":1.97,"deg":183,"gust":4.1},"clouds":{"all":0},"dt":1724806840,"sys":{"type":2,"id":2007844,"country":"US","sunrise":1724755961,"sunset":1724803035},"timezone":-14400,"id":4460243,"name":"Charlotte","cod":200}