{"coord":{"lon":-83.0458,"lat":42.3314},"weather":[{"id":803,"main":"Clouds","description":"broken clouds","icon":"04n"}],"base":"stations","main":{"temp":22.03,"feels_like":22.74,"temp_min":22.03,"temp_max":22.97,"pressure":1013,"humidity":94,"sea_level":1013,"grnd_level":992},"visibility":10000,"wind":{"speed":5.14,"deg":220},"clouds":{"all":75},"dt":1724807192,"sys":{"type":1,"id":892,"country":"US","sunrise":1724755970,"sunset":1724804084},"timezone":-14400,"id":4990729,"name":"Detroit","cod":200}